{
  "acquisition": {
    "pixels_x": 2145,
    "pixels_y": 2145,
    "image_type": "dermoscopic"
  },
  "clinical": {
    "concomitant_biopsy": true,
    "sex": "female",
    "anatom_site_general": "lower extremity",
    "benign_malignant": "benign",
    "diagnosis_1": "Benign",
    "diagnosis_2": "Benign melanocytic proliferations",
    "diagnosis_3": "Nevus",
    "diagnosis_4": "Nevus, Atypical, Dysplastic, or Clark",
    "diagnosis_confirm_type": "histopathology",
    "clin_size_long_diam_mm": "5.70",
    "melanocytic": true,
    "age_approx": 40,
    "lesion_id": "IL_5383957",
    "patient_id": "IP_5169973",
    "diagnosis": "nevus"
  }
}