{
  "acquisition": {
    "pixels_x": 113,
    "pixels_y": 113,
    "image_type": "TBP tile: close-up"
  },
  "clinical": {
    "sex": "male",
    "anatom_site_general": "lower extremity",
    "benign_malignant": "benign",
    "diagnosis_1": "Benign",
    "diagnosis_2": "Benign melanocytic proliferations",
    "diagnosis_3": "Nevus",
    "diagnosis_4": "Nevus, Of special anatomic site",
    "diagnosis_confirm_type": "histopathology",
    "clin_size_long_diam_mm": "2.91",
    "nevus_type": "special site",
    "tbp_tile_type": "3D: white",
    "age_approx": 50,
    "lesion_id": "IL_5502727",
    "patient_id": "IP_1255419",
    "diagnosis": "nevus"
  }
}